markitdown_mcp/__about__.py
markitdown_mcp/__init__.py
markitdown_mcp/__main__.py
markitdown_mcp/py.typed
markitdown_mcp-0.0.1a3.dist-info/METADATA
markitdown_mcp-0.0.1a3.dist-info/WHEEL
markitdown_mcp-0.0.1a3.dist-info/entry_points.txt
markitdown_mcp-0.0.1a3.dist-info/RECORD
