Metadata-Version: 2.4
Name: markitdown-mcp
Version: 0.0.1a3
Summary: An MCP server for the "markitdown" library.
Project-URL: Documentation, https://github.com/microsoft/markitdown#readme
Project-URL: Issues, https://github.com/microsoft/markitdown/issues
Project-URL: Source, https://github.com/microsoft/markitdown
Author-email: Adam Fourney <adamfo@microsoft.com>
License-Expression: MIT
Classifier: Development Status :: 4 - Beta
Classifier: Programming Language :: Python
Classifier: Programming Language :: Python :: 3.10
Classifier: Programming Language :: Python :: 3.11
Classifier: Programming Language :: Python :: 3.12
Classifier: Programming Language :: Python :: 3.13
Classifier: Programming Language :: Python :: Implementation :: CPython
Classifier: Programming Language :: Python :: Implementation :: PyPy
Requires-Python: >=3.10
Requires-Dist: markitdown[all]<0.2.0,>=0.1.1
Requires-Dist: mcp
